accusleepy/__init__.py
accusleepy/__main__.py
accusleepy/bouts.py
accusleepy/brain_state_set.py
accusleepy/classification.py
accusleepy/config.json
accusleepy/constants.py
accusleepy/fileio.py
accusleepy/gui/__init__.py
accusleepy/gui/dialogs.py
accusleepy/gui/icons/brightness_down.png
accusleepy/gui/icons/brightness_up.png
accusleepy/gui/icons/double_down_arrow.png
accusleepy/gui/icons/double_up_arrow.png
accusleepy/gui/icons/down_arrow.png
accusleepy/gui/icons/home.png
accusleepy/gui/icons/question.png
accusleepy/gui/icons/save.png
accusleepy/gui/icons/up_arrow.png
accusleepy/gui/icons/zoom_in.png
accusleepy/gui/icons/zoom_out.png
accusleepy/gui/images/primary_window.png
accusleepy/gui/images/viewer_window.png
accusleepy/gui/images/viewer_window_annotated.png
accusleepy/gui/main.py
accusleepy/gui/manual_scoring.py
accusleepy/gui/mplwidget.py
accusleepy/gui/primary_window.py
accusleepy/gui/primary_window.ui
accusleepy/gui/recording_manager.py
accusleepy/gui/resources.qrc
accusleepy/gui/resources_rc.py
accusleepy/gui/settings_widget.py
accusleepy/gui/text/dev_guide.md
accusleepy/gui/text/main_guide.md
accusleepy/gui/text/manual_scoring_guide.md
accusleepy/gui/viewer_window.py
accusleepy/gui/viewer_window.ui
accusleepy/models.py
accusleepy/multitaper.py
accusleepy/services.py
accusleepy/signal_processing.py
accusleepy/temperature_scaling.py
accusleepy/validation.py
accusleepy-0.10.0.dist-info/METADATA
accusleepy-0.10.0.dist-info/WHEEL
accusleepy-0.10.0.dist-info/RECORD
