Metadata-Version: 2.4
Name: accusleepy
Version: 0.10.0
Summary: Python implementation of AccuSleep
License: GPL-3.0-only
Author: Zeke Barger
Author-email: zekebarger@gmail.com
Requires-Python: >=3.11,<3.14
Classifier: License :: OSI Approved :: GNU General Public License v3 (GPLv3)
Classifier: Programming Language :: Python :: 3
Classifier: Programming Language :: Python :: 3.11
Classifier: Programming Language :: Python :: 3.12
Classifier: Programming Language :: Python :: 3.13
Requires-Dist: fastparquet (>=2024.11.0,<2025.0.0)
Requires-Dist: joblib (>=1.4.2,<2.0.0)
Requires-Dist: matplotlib (>=3.10.1,<4.0.0)
Requires-Dist: numpy (>=2.2.4,<3.0.0)
Requires-Dist: pandas (>=2.2.3,<3.0.0)
Requires-Dist: pillow (>=11.1.0,<12.0.0)
Requires-Dist: pre-commit (>=4.2.0,<5.0.0)
Requires-Dist: pyside6 (>=6.9.0,<6.9.3)
Requires-Dist: scipy (>=1.15.2,<2.0.0)
Requires-Dist: torch (>=2.8.0,<3.0.0)
Requires-Dist: torchvision (>=0.23.0,<1.0.0)
Requires-Dist: tqdm (>=4.67.1,<5.0.0)
